CHANGES.rst
CONTRIBUTORS.rst
DEVELOP.rst
LICENSE.GPL
LICENSE.rst
MANIFEST.in
README.rst
constraints.txt
requirements.txt
setup.cfg
setup.py
tox.ini
collective/__init__.py
collective.portlet.existingcontent.egg-info/PKG-INFO
collective.portlet.existingcontent.egg-info/SOURCES.txt
collective.portlet.existingcontent.egg-info/dependency_links.txt
collective.portlet.existingcontent.egg-info/entry_points.txt
collective.portlet.existingcontent.egg-info/namespace_packages.txt
collective.portlet.existingcontent.egg-info/not-zip-safe
collective.portlet.existingcontent.egg-info/requires.txt
collective.portlet.existingcontent.egg-info/top_level.txt
collective/portlet/__init__.py
collective/portlet/existingcontent/__init__.py
collective/portlet/existingcontent/configure.zcml
collective/portlet/existingcontent/interfaces.py
collective/portlet/existingcontent/portlet.pt
collective/portlet/existingcontent/portlet.py
collective/portlet/existingcontent/setuphandlers.py
collective/portlet/existingcontent/testing.py
collective/portlet/existingcontent/locales/README.rst
collective/portlet/existingcontent/locales/__init__.py
collective/portlet/existingcontent/locales/collective.portlet.existingcontent.pot
collective/portlet/existingcontent/locales/update.py
collective/portlet/existingcontent/locales/update.sh
collective/portlet/existingcontent/locales/de/LC_MESSAGES/collective.portlet.existingcontent.mo
collective/portlet/existingcontent/locales/de/LC_MESSAGES/collective.portlet.existingcontent.po
collective/portlet/existingcontent/locales/en/LC_MESSAGES/collective.portlet.existingcontent.mo
collective/portlet/existingcontent/locales/en/LC_MESSAGES/collective.portlet.existingcontent.po
collective/portlet/existingcontent/profiles/default/browserlayer.xml
collective/portlet/existingcontent/profiles/default/metadata.xml
collective/portlet/existingcontent/profiles/default/portlets.xml
collective/portlet/existingcontent/profiles/default/registry.xml
collective/portlet/existingcontent/profiles/uninstall/browserlayer.xml
collective/portlet/existingcontent/tests/__init__.py
collective/portlet/existingcontent/tests/test_portlet.py
collective/portlet/existingcontent/tests/test_setup.py