Metadata-Version: 2.1
Name: collective.portlet.existingcontent
Version: 1.0.4
Summary: Existing Content Portlet
Home-page: https://github.com/collective/collective.portlet.existingcontent
Author: Markus Hilbert
Author-email: markus.hilbert@iham.at
License: GPL version 2
Keywords: Python Plone
Platform: UNKNOWN
Classifier: Environment :: Web Environment
Classifier: Framework :: Plone
Classifier: Framework :: Plone :: Addon
Classifier: Framework :: Plone :: 5.2
Classifier: Programming Language :: Python
Classifier: Programming Language :: Python :: 2.7
Classifier: Programming Language :: Python :: 3.7
Classifier: Operating System :: OS Independent
Classifier: License :: OSI Approved :: GNU General Public License v2 (GPLv2)
Provides-Extra: test
